pyemfield/__init__.py
pyemfield/ffd.py
pyemfield-0.1.6.dist-info/LICENSE
pyemfield-0.1.6.dist-info/METADATA
pyemfield-0.1.6.dist-info/WHEEL
pyemfield-0.1.6.dist-info/top_level.txt
pyemfield-0.1.6.dist-info/RECORD
