Metadata-Version: 2.1
Name: pyemfield
Version: 0.1.6
Summary: A Python library for HFSS antenna radiation pattern analysis and gain optimization
Home-page: https://github.com/linmingchih/pyemfield
Author: Lin, Ming Chih
Author-email: mingchih.lin8@gmail.com
Classifier: Programming Language :: Python :: 3
Classifier: License :: OSI Approved :: MIT License
Classifier: Operating System :: OS Independent
Requires-Python: >=3.6
License-File: LICENSE
Requires-Dist: numpy>=1.18.0
Requires-Dist: scipy>=1.4.0
Requires-Dist: matplotlib>=3.1.0
Requires-Dist: pyaedt>=0.10.1
